{
  "name": "Jak",
  "translation": "",
  "artist": "Zedes",
  "lines": [
    {
      "line": "គោលដៅចាស់ដំណើរថ្មី រឿងគ្រប់យ៉ាងខ្ញុំលកលៃ",
      "translation": "Old goals, new journeys, everything I do",
      "phonetic": "koldaw chasa damnaer thmei  rueng krobyeang khnhom l klei",
      "words": [
        {
          "word": "គោលដៅ",
          "phonetic": "koldaw",
          "translation": "Goal"
        },
        {
          "word": "ចាស់",
          "phonetic": "chasa",
          "translation": "Old"
        },
        {
          "word": "ដំណើរ",
          "phonetic": "damnaer",
          "translation": "Journey"
        },
        {
          "word": "ថ្មី",
          "phonetic": "thmei",
          "translation": "New"
        },
        {
          "word": "រឿង",
          "phonetic": "rueng",
          "translation": "Story"
        },
        {
          "word": "គ្រប់យ៉ាង",
          "phonetic": "krobyeang",
          "translation": "Everything"
        },
        {
          "word": "ខ្ញុំ",
          "phonetic": "khnhom",
          "translation": "I"
        },
        {
          "word": "លកលៃ",
          "phonetic": "l klei",
          "translation": "Adjustment"
        }
      ]
    },
    {
      "line": "Yeah yeah",
      "translation": "Yeah yeah",
      "phonetic": "yeah yeah",
      "words": [
        {
          "word": "Yeah",
          "phonetic": "",
          "translation": "Yeah"
        },
        {
          "word": "yeah",
          "phonetic": "yeah",
          "translation": "yeah"
        }
      ]
    },
    {
      "line": "គោលដៅចាស់ដំណើរថ្មី រឿងគ្រប់យ៉ាងខ្ញុំលកលៃ",
      "translation": "Old goals, new journeys, everything I do",
      "phonetic": "koldaw chasa damnaer thmei  rueng krobyeang khnhom l klei",
      "words": [
        {
          "word": "គោលដៅ",
          "phonetic": "koldaw",
          "translation": "Goal"
        },
        {
          "word": "ចាស់",
          "phonetic": "chasa",
          "translation": "Old"
        },
        {
          "word": "ដំណើរ",
          "phonetic": "damnaer",
          "translation": "Journey"
        },
        {
          "word": "ថ្មី",
          "phonetic": "thmei",
          "translation": "New"
        },
        {
          "word": "រឿង",
          "phonetic": "rueng",
          "translation": "Story"
        },
        {
          "word": "គ្រប់យ៉ាង",
          "phonetic": "krobyeang",
          "translation": "Everything"
        },
        {
          "word": "ខ្ញុំ",
          "phonetic": "khnhom",
          "translation": "I"
        },
        {
          "word": "លកលៃ",
          "phonetic": "l klei",
          "translation": "Adjustment"
        }
      ]
    },
    {
      "line": "ខំប្រឹងជីកកកាយរិះរកគ្រប់ផ្លូវ ទៅកាន់ភាពជោគជ័យ",
      "translation": "Strive to find all the path to success",
      "phonetic": "khambroeng chikakkeay riahrk krobphlauv  towkean pheap chokchy",
      "words": [
        {
          "word": "ខំប្រឹង",
          "phonetic": "khambroeng",
          "translation": "Try hard"
        },
        {
          "word": "ជីក",
          "phonetic": "chik",
          "translation": "Dig"
        },
        {
          "word": "កកាយ",
          "phonetic": "kkay",
          "translation": "Body"
        },
        {
          "word": "រិះរក",
          "phonetic": "riahrk",
          "translation": "Search"
        },
        {
          "word": "គ្រប់ផ្លូវ",
          "phonetic": "krobphlauv",
          "translation": "All the way"
        },
        {
          "word": "ទៅកាន់",
          "phonetic": "towkean",
          "translation": "To"
        },
        {
          "word": "ភាព",
          "phonetic": "pheap",
          "translation": "Availability"
        },
        {
          "word": "ជោគជ័យ",
          "phonetic": "chokchy",
          "translation": "Success"
        }
      ]
    },
    {
      "line": "គោលដៅចាស់ដំណើរថ្មី រឿងគ្រប់យ៉ាងខ្ញុំលកលៃ",
      "translation": "Old goals, new journeys, everything I do",
      "phonetic": "koldaw chasa damnaer thmei  rueng krobyeang khnhom l klei",
      "words": [
        {
          "word": "គោលដៅ",
          "phonetic": "koldaw",
          "translation": "Goal"
        },
        {
          "word": "ចាស់",
          "phonetic": "chasa",
          "translation": "Old"
        },
        {
          "word": "ដំណើរ",
          "phonetic": "damnaer",
          "translation": "Journey"
        },
        {
          "word": "ថ្មី",
          "phonetic": "thmei",
          "translation": "New"
        },
        {
          "word": "រឿង",
          "phonetic": "rueng",
          "translation": "Story"
        },
        {
          "word": "គ្រប់យ៉ាង",
          "phonetic": "krobyeang",
          "translation": "Everything"
        },
        {
          "word": "ខ្ញុំ",
          "phonetic": "khnhom",
          "translation": "I"
        },
        {
          "word": "លកលៃ",
          "phonetic": "l klei",
          "translation": "Adjustment"
        }
      ]
    },
    {
      "line": "ខំប្រឹងជីកកកាយរិះរកគ្រប់ផ្លូវ ទៅកាន់ភាពជោគជ័យ",
      "translation": "Strive to find all the path to success",
      "phonetic": "khambroeng chikakkeay riahrk krobphlauv  towkean pheap chokchy",
      "words": [
        {
          "word": "ខំប្រឹង",
          "phonetic": "khambroeng",
          "translation": "Try hard"
        },
        {
          "word": "ជីក",
          "phonetic": "chik",
          "translation": "Dig"
        },
        {
          "word": "កកាយ",
          "phonetic": "kkay",
          "translation": "Body"
        },
        {
          "word": "រិះរក",
          "phonetic": "riahrk",
          "translation": "Search"
        },
        {
          "word": "គ្រប់ផ្លូវ",
          "phonetic": "krobphlauv",
          "translation": "All the way"
        },
        {
          "word": "ទៅកាន់",
          "phonetic": "towkean",
          "translation": "To"
        },
        {
          "word": "ភាព",
          "phonetic": "pheap",
          "translation": "Availability"
        },
        {
          "word": "ជោគជ័យ",
          "phonetic": "chokchy",
          "translation": "Success"
        }
      ]
    },
    {
      "break": true
    },
    {
      "line": "ចូលក្រុងរកកំណប់ រកលុយជូនគ្រួសារ",
      "translation": "Enter the city to find treasure to earn money for the family",
      "phonetic": "chaul krong rk kamnb  roklouy choun kruosaear",
      "words": [
        {
          "word": "ចូល",
          "phonetic": "chaul",
          "translation": "Login"
        },
        {
          "word": "ក្រុង",
          "phonetic": "krong",
          "translation": "City"
        },
        {
          "word": "រក",
          "phonetic": "rk",
          "translation": "Find"
        },
        {
          "word": "កំណប់",
          "phonetic": "kamnb",
          "translation": "Treasure"
        },
        {
          "word": "រកលុយ",
          "phonetic": "roklouy",
          "translation": "Make money"
        },
        {
          "word": "ជូន",
          "phonetic": "choun",
          "translation": "To"
        },
        {
          "word": "គ្រួសារ",
          "phonetic": "kruosaear",
          "translation": "Family"
        }
      ]
    },
    {
      "line": "ប៉ុន្មានឆ្នាំនេះចង់សន្លប់ ដណ្តប់ភួយដូចដណ្តប់ផ្កា",
      "translation": "These years I want to faintly cover the blanket like a flower",
      "phonetic": "bonman chhnam nih chng sanlob  dantabphuoy dauch d nt b phka",
      "words": [
        {
          "word": "ប៉ុន្មាន",
          "phonetic": "bonman",
          "translation": "How much"
        },
        {
          "word": "ឆ្នាំ",
          "phonetic": "chhnam",
          "translation": "Years"
        },
        {
          "word": "នេះ",
          "phonetic": "nih",
          "translation": "This"
        },
        {
          "word": "ចង់",
          "phonetic": "chng",
          "translation": "Want"
        },
        {
          "word": "សន្លប់",
          "phonetic": "sanlob",
          "translation": "Unconscious"
        },
        {
          "word": "ដណ្តប់",
          "phonetic": "d nt b",
          "translation": "Cover"
        },
        {
          "word": "ភួយ",
          "phonetic": "phuoy",
          "translation": "Blanket"
        },
        {
          "word": "ដូច",
          "phonetic": "dauch",
          "translation": "Like"
        },
        {
          "word": "ដណ្តប់",
          "phonetic": "d nt b",
          "translation": "Cover"
        },
        {
          "word": "ផ្កា",
          "phonetic": "phka",
          "translation": "Flowers"
        }
      ]
    },
    {
      "line": "តែពេលនេះថ្ងៃនេះខ្ញុំអ្នកកប់ សពពួកអាចិត្តឬស្យា",
      "translation": "But now, today, I am the one who bury the spirits.",
      "phonetic": "te pelnih thngainih khnhom anak kb  sa ppuok a chett ryy sya",
      "words": [
        {
          "word": "តែ",
          "phonetic": "te",
          "translation": "Tea"
        },
        {
          "word": "ពេលនេះ",
          "phonetic": "pelnih",
          "translation": "Now"
        },
        {
          "word": "ថ្ងៃនេះ",
          "phonetic": "thngainih",
          "translation": "Today"
        },
        {
          "word": "ខ្ញុំ",
          "phonetic": "khnhom",
          "translation": "I"
        },
        {
          "word": "អ្នក",
          "phonetic": "anak",
          "translation": "You"
        },
        {
          "word": "កប់",
          "phonetic": "kb",
          "translation": "Bury"
        },
        {
          "word": "សព",
          "phonetic": "sap",
          "translation": "Corpse"
        },
        {
          "word": "ពួក",
          "phonetic": "puok",
          "translation": "They"
        },
        {
          "word": "អា",
          "phonetic": "a",
          "translation": "Ah"
        },
        {
          "word": "ចិត្ត",
          "phonetic": "chett",
          "translation": "Mind"
        },
        {
          "word": "ឬ",
          "phonetic": "ryy",
          "translation": "Or"
        },
        {
          "word": "ស្យា",
          "phonetic": "sya",
          "translation": "ស្យា"
        }
      ]
    },
    {
      "line": "ពួកអានេះវាពូកែសន្លប់ នៅមុខវាដូចអ្នកតា",
      "translation": "They are as good at fainting in front of you as you are",
      "phonetic": "puok a nih vea pouke sanlob  nowmoukh vea dauch anak ta",
      "words": [
        {
          "word": "ពួក",
          "phonetic": "puok",
          "translation": "They"
        },
        {
          "word": "អានេះ",
          "phonetic": "anih",
          "translation": "Ah this"
        },
        {
          "word": "វា",
          "phonetic": "vea",
          "translation": "It"
        },
        {
          "word": "ពូកែ",
          "phonetic": "pouke",
          "translation": "Outstanding"
        },
        {
          "word": "សន្លប់",
          "phonetic": "sanlob",
          "translation": "Unconscious"
        },
        {
          "word": "នៅមុខ",
          "phonetic": "nowmoukh",
          "translation": "In front"
        },
        {
          "word": "វា",
          "phonetic": "vea",
          "translation": "It"
        },
        {
          "word": "ដូច",
          "phonetic": "dauch",
          "translation": "Like"
        },
        {
          "word": "អ្នកតា",
          "phonetic": "anaktea",
          "translation": "Nephew"
        }
      ]
    },
    {
      "break": true
    },
    {
      "line": "វាមុខមួយ មុខពីរ មុខបី មុខ1០០០ក្តី",
      "translation": "It's one face, two faces, three faces, 1,000 cases",
      "phonetic": "vea moukh muoy  moukh pir  moukh bei  moukh1 0 0 0ktei",
      "words": [
        {
          "word": "វា",
          "phonetic": "vea",
          "translation": "It"
        },
        {
          "word": "មុខ",
          "phonetic": "moukh",
          "translation": "Face"
        },
        {
          "word": "មួយ",
          "phonetic": "muoy",
          "translation": "One"
        },
        {
          "word": "មុខ",
          "phonetic": "moukh",
          "translation": "Face"
        },
        {
          "word": "ពីរ",
          "phonetic": "pir",
          "translation": "Two"
        },
        {
          "word": "មុខ",
          "phonetic": "moukh",
          "translation": "Face"
        },
        {
          "word": "បី",
          "phonetic": "bei",
          "translation": "Three"
        },
        {
          "word": "មុខ",
          "phonetic": "moukh",
          "translation": "Face"
        },
        {
          "word": "1",
          "phonetic": "",
          "translation": "1"
        },
        {
          "word": "០០០",
          "phonetic": "0 00",
          "translation": "000"
        },
        {
          "word": "ក្តី",
          "phonetic": "ktei",
          "translation": "Case"
        }
      ]
    },
    {
      "line": "ក្តីវាអត់ស្រៈអី សមក្បាលមួយកៅអី",
      "translation": "It does not fit a chair",
      "phonetic": "ktei vea at sr ei  sam kbal muoy kawei",
      "words": [
        {
          "word": "ក្តី",
          "phonetic": "ktei",
          "translation": "Case"
        },
        {
          "word": "វា",
          "phonetic": "vea",
          "translation": "It"
        },
        {
          "word": "អត់",
          "phonetic": "at",
          "translation": "No"
        },
        {
          "word": "ស្រៈ",
          "phonetic": "sr",
          "translation": "Vowel"
        },
        {
          "word": "អី",
          "phonetic": "ei",
          "translation": "What"
        },
        {
          "word": "សម",
          "phonetic": "sam",
          "translation": "Fit"
        },
        {
          "word": "ក្បាល",
          "phonetic": "kbal",
          "translation": "Head"
        },
        {
          "word": "មួយ",
          "phonetic": "muoy",
          "translation": "One"
        },
        {
          "word": "កៅអី",
          "phonetic": "kawei",
          "translation": "Chair"
        }
      ]
    },
    {
      "line": "ពួកអាតិរថី វក់ស្រីវក់ស្រា",
      "translation": "Veterans are addicted to alcohol",
      "phonetic": "puok a te rthei  vk srei vksra",
      "words": [
        {
          "word": "ពួក",
          "phonetic": "puok",
          "translation": "They"
        },
        {
          "word": "អា",
          "phonetic": "a",
          "translation": "Ah"
        },
        {
          "word": "តិ",
          "phonetic": "te",
          "translation": "តិ"
        },
        {
          "word": "រ",
          "phonetic": "r",
          "translation": "រ"
        },
        {
          "word": "ថី",
          "phonetic": "thei",
          "translation": "New"
        },
        {
          "word": "វក់",
          "phonetic": "vk",
          "translation": "Busy"
        },
        {
          "word": "ស្រី",
          "phonetic": "srei",
          "translation": "Female"
        },
        {
          "word": "វក់",
          "phonetic": "vk",
          "translation": "Busy"
        },
        {
          "word": "ស្រា",
          "phonetic": "sra",
          "translation": "Wine"
        }
      ]
    },
    {
      "line": "សំបុត្រនរកអវចី ចាំអញអ្នកបោះត្រា",
      "translation": "Hell letter, I remember you stamp",
      "phonetic": "saambotr nork a vchei  cham anh anak baohtra",
      "words": [
        {
          "word": "សំបុត្រ",
          "phonetic": "saambotr",
          "translation": "Tickets"
        },
        {
          "word": "នរក",
          "phonetic": "nork",
          "translation": "Hell"
        },
        {
          "word": "អវ",
          "phonetic": "av",
          "translation": "Av"
        },
        {
          "word": "ចី",
          "phonetic": "chei",
          "translation": "Chi"
        },
        {
          "word": "ចាំ",
          "phonetic": "cham",
          "translation": "Remember"
        },
        {
          "word": "អញ",
          "phonetic": "anh",
          "translation": "I"
        },
        {
          "word": "អ្នក",
          "phonetic": "anak",
          "translation": "You"
        },
        {
          "word": "បោះត្រា",
          "phonetic": "baohtra",
          "translation": "Seal"
        }
      ]
    },
    {
      "break": true
    },
    {
      "line": "ស្លូតពេកក្លាយជាទាសករ",
      "translation": "Too innocent to be a slave",
      "phonetic": "slaut pek klaycha teasakr",
      "words": [
        {
          "word": "ស្លូត",
          "phonetic": "slaut",
          "translation": "Innocent"
        },
        {
          "word": "ពេក",
          "phonetic": "pek",
          "translation": "Too"
        },
        {
          "word": "ក្លាយ",
          "phonetic": "klay",
          "translation": "Become"
        },
        {
          "word": "ជា",
          "phonetic": "chea",
          "translation": "Is"
        },
        {
          "word": "ទាសករ",
          "phonetic": "teasakr",
          "translation": "Slave"
        }
      ]
    },
    {
      "line": "កាចពេកក្លាយជាឃាតករ",
      "translation": "Too cruel to be a killer",
      "phonetic": "kach pek klaycha kheatakr",
      "words": [
        {
          "word": "កាច",
          "phonetic": "kach",
          "translation": "Angry"
        },
        {
          "word": "ពេក",
          "phonetic": "pek",
          "translation": "Too"
        },
        {
          "word": "ក្លាយ",
          "phonetic": "klay",
          "translation": "Become"
        },
        {
          "word": "ជា",
          "phonetic": "chea",
          "translation": "Is"
        },
        {
          "word": "ឃាតករ",
          "phonetic": "kheatakr",
          "translation": "Killer"
        }
      ]
    },
    {
      "line": "I TRYNA BREAK THEIR LAWS",
      "translation": "I TRYNA BREAK THEIR LAWS",
      "phonetic": "i tryna break their laws",
      "words": [
        {
          "word": "I",
          "phonetic": "",
          "translation": "I"
        },
        {
          "word": "TRYNA",
          "phonetic": "",
          "translation": "TRYNA"
        },
        {
          "word": "BREAK",
          "phonetic": "",
          "translation": "BREAK"
        },
        {
          "word": "THEIR",
          "phonetic": "",
          "translation": "THEIR"
        },
        {
          "word": "LAWS",
          "phonetic": "",
          "translation": "LAWS"
        }
      ]
    },
    {
      "line": "THEY SCARED AND THEY LOCK THEIR DOORS",
      "translation": "THEY SCARED AND THEY LOCK THEIR DOORS",
      "phonetic": "they scared and they lock their doors",
      "words": [
        {
          "word": "THEY",
          "phonetic": "",
          "translation": "THEY"
        },
        {
          "word": "SCARED",
          "phonetic": "",
          "translation": "SCARED"
        },
        {
          "word": "AND",
          "phonetic": "",
          "translation": "AND"
        },
        {
          "word": "THEY",
          "phonetic": "",
          "translation": "THEY"
        },
        {
          "word": "LOCK",
          "phonetic": "",
          "translation": "LOCK"
        },
        {
          "word": "THEIR",
          "phonetic": "",
          "translation": "THEIR"
        },
        {
          "word": "DOORS",
          "phonetic": "",
          "translation": "DOORS"
        }
      ]
    },
    {
      "break": true
    },
    {
      "line": "គេថាគេមានលុយទាំងលាន ខ្ញុំមានត្រឹមអង្ករមួយតៅ",
      "translation": "They say they have millions, I only have one ton of rice",
      "phonetic": "ke tha ke mean louy teang lean  khnhom mean troem angkor muoy taw",
      "words": [
        {
          "word": "គេ",
          "phonetic": "ke",
          "translation": "They"
        },
        {
          "word": "ថា",
          "phonetic": "tha",
          "translation": "That"
        },
        {
          "word": "គេ",
          "phonetic": "ke",
          "translation": "They"
        },
        {
          "word": "មាន",
          "phonetic": "mean",
          "translation": "Have"
        },
        {
          "word": "លុយ",
          "phonetic": "louy",
          "translation": "Money"
        },
        {
          "word": "ទាំង",
          "phonetic": "teang",
          "translation": "Both"
        },
        {
          "word": "លាន",
          "phonetic": "lean",
          "translation": "Million"
        },
        {
          "word": "ខ្ញុំ",
          "phonetic": "khnhom",
          "translation": "I"
        },
        {
          "word": "មាន",
          "phonetic": "mean",
          "translation": "Have"
        },
        {
          "word": "ត្រឹម",
          "phonetic": "troem",
          "translation": "Just"
        },
        {
          "word": "អង្ករ",
          "phonetic": "angkor",
          "translation": "Rice"
        },
        {
          "word": "មួយ",
          "phonetic": "muoy",
          "translation": "One"
        },
        {
          "word": "តៅ",
          "phonetic": "taw",
          "translation": "Tao"
        }
      ]
    },
    {
      "line": "ខ្ញុំអត់មានអីសណ្តោង ដើរអាយីង អាយោងពេញផ្លូវ",
      "translation": "I do not have a trailer to walk all the way",
      "phonetic": "khnhom atmean ei sa ntaong  daer a ying  a yong penh phlauv",
      "words": [
        {
          "word": "ខ្ញុំ",
          "phonetic": "khnhom",
          "translation": "I"
        },
        {
          "word": "អត់មាន",
          "phonetic": "atmean",
          "translation": "None"
        },
        {
          "word": "អី",
          "phonetic": "ei",
          "translation": "What"
        },
        {
          "word": "សណ្តោង",
          "phonetic": "sa ntaong",
          "translation": "Trailer"
        },
        {
          "word": "ដើរ",
          "phonetic": "daer",
          "translation": "Walk"
        },
        {
          "word": "អាយីង",
          "phonetic": "a ying",
          "translation": "Ai Ying"
        },
        {
          "word": "អាយោង",
          "phonetic": "a yong",
          "translation": "References"
        },
        {
          "word": "ពេញ",
          "phonetic": "penh",
          "translation": "Full"
        },
        {
          "word": "ផ្លូវ",
          "phonetic": "phlauv",
          "translation": "Road"
        }
      ]
    },
    {
      "line": "តែខ្ញុំចង់ក្លាយជាទេពច្យុត អាចហោះហើរផុតសមុទ្រ",
      "translation": "But I want to be a magician who can fly over the sea",
      "phonetic": "te khnhom chng klaycha tepochyot  ach haohhaer phot samout",
      "words": [
        {
          "word": "តែ",
          "phonetic": "te",
          "translation": "Tea"
        },
        {
          "word": "ខ្ញុំ",
          "phonetic": "khnhom",
          "translation": "I"
        },
        {
          "word": "ចង់",
          "phonetic": "chng",
          "translation": "Want"
        },
        {
          "word": "ក្លាយ",
          "phonetic": "klay",
          "translation": "Become"
        },
        {
          "word": "ជា",
          "phonetic": "chea",
          "translation": "Is"
        },
        {
          "word": "ទេពច្យុត",
          "phonetic": "tepochyot",
          "translation": "Tep Chyut"
        },
        {
          "word": "អាច",
          "phonetic": "ach",
          "translation": "Can"
        },
        {
          "word": "ហោះហើរ",
          "phonetic": "haohhaer",
          "translation": "To fly"
        },
        {
          "word": "ផុត",
          "phonetic": "phot",
          "translation": "Out"
        },
        {
          "word": "សមុទ្រ",
          "phonetic": "samoutr",
          "translation": "The sea"
        }
      ]
    },
    {
      "line": "គេថាសម្តីខ្ញុំឡូយ ក៏ព្រោះតែសម្តីខ្ញុំមុត",
      "translation": "They say my words are cool because my words are sharp",
      "phonetic": "ke tha sa mti khnhom lauy  ka prohte sa mti khnhom mout",
      "words": [
        {
          "word": "គេ",
          "phonetic": "ke",
          "translation": "They"
        },
        {
          "word": "ថា",
          "phonetic": "tha",
          "translation": "That"
        },
        {
          "word": "សម្តី",
          "phonetic": "sa mti",
          "translation": "Speech"
        },
        {
          "word": "ខ្ញុំ",
          "phonetic": "khnhom",
          "translation": "I"
        },
        {
          "word": "ឡូយ",
          "phonetic": "lauy",
          "translation": "Cool"
        },
        {
          "word": "ក៏",
          "phonetic": "ka",
          "translation": "Also"
        },
        {
          "word": "ព្រោះតែ",
          "phonetic": "prohte",
          "translation": "Because"
        },
        {
          "word": "សម្តី",
          "phonetic": "sa mti",
          "translation": "Speech"
        },
        {
          "word": "ខ្ញុំ",
          "phonetic": "khnhom",
          "translation": "I"
        },
        {
          "word": "មុត",
          "phonetic": "mout",
          "translation": "Sharp"
        }
      ]
    },
    {
      "break": true
    },
    {
      "line": "ខ្ញុំចង់ក្លាយជាទេពច្យុត អាចហោះហើរផុតសមុទ្រ",
      "translation": "I want to be a magician who can fly over the sea",
      "phonetic": "khnhom chng klaycha tepochyot  ach haohhaer phot samoutr",
      "words": [
        {
          "word": "ខ្ញុំ",
          "phonetic": "khnhom",
          "translation": "I"
        },
        {
          "word": "ចង់",
          "phonetic": "chng",
          "translation": "Want"
        },
        {
          "word": "ក្លាយ",
          "phonetic": "klay",
          "translation": "Become"
        },
        {
          "word": "ជា",
          "phonetic": "chea",
          "translation": "Is"
        },
        {
          "word": "ទេពច្យុត",
          "phonetic": "tepochyot",
          "translation": "Tep Chyut"
        },
        {
          "word": "អាច",
          "phonetic": "ach",
          "translation": "Can"
        },
        {
          "word": "ហោះហើរ",
          "phonetic": "haohhaer",
          "translation": "To fly"
        },
        {
          "word": "ផុត",
          "phonetic": "phot",
          "translation": "Out"
        },
        {
          "word": "សមុទ្រ",
          "phonetic": "samoutr",
          "translation": "The sea"
        }
      ]
    },
    {
      "line": "គេថាសម្តីខ្ញុំឡូយ ក៏ព្រោះតែសម្តីខ្ញុំមុត",
      "translation": "They say my words are cool because my words are sharp",
      "phonetic": "ke tha sa mti khnhom lauy  ka prohte sa mti khnhom mout",
      "words": [
        {
          "word": "គេ",
          "phonetic": "ke",
          "translation": "They"
        },
        {
          "word": "ថា",
          "phonetic": "tha",
          "translation": "That"
        },
        {
          "word": "សម្តី",
          "phonetic": "sa mti",
          "translation": "Speech"
        },
        {
          "word": "ខ្ញុំ",
          "phonetic": "khnhom",
          "translation": "I"
        },
        {
          "word": "ឡូយ",
          "phonetic": "lauy",
          "translation": "Cool"
        },
        {
          "word": "ក៏",
          "phonetic": "ka",
          "translation": "Also"
        },
        {
          "word": "ព្រោះតែ",
          "phonetic": "prohte",
          "translation": "Because"
        },
        {
          "word": "សម្តី",
          "phonetic": "sa mti",
          "translation": "Speech"
        },
        {
          "word": "ខ្ញុំ",
          "phonetic": "khnhom",
          "translation": "I"
        },
        {
          "word": "មុត",
          "phonetic": "mout",
          "translation": "Sharp"
        }
      ]
    },
    {
      "line": "ហើយគេថា ម្តេចបានខ្ញុំនេះមុខបាក់",
      "translation": "And how can they say that I am broken?",
      "phonetic": "haey ke tha  mte ch ban khnhom nih moukh bak",
      "words": [
        {
          "word": "ហើយ",
          "phonetic": "haey",
          "translation": "And"
        },
        {
          "word": "គេ",
          "phonetic": "ke",
          "translation": "They"
        },
        {
          "word": "ថា",
          "phonetic": "tha",
          "translation": "That"
        },
        {
          "word": "ម្តេច",
          "phonetic": "mte ch",
          "translation": "How"
        },
        {
          "word": "បាន",
          "phonetic": "ban",
          "translation": "Yes"
        },
        {
          "word": "ខ្ញុំ",
          "phonetic": "khnhom",
          "translation": "I"
        },
        {
          "word": "នេះ",
          "phonetic": "nih",
          "translation": "This"
        },
        {
          "word": "មុខ",
          "phonetic": "moukh",
          "translation": "Face"
        },
        {
          "word": "បាក់",
          "phonetic": "bak",
          "translation": "Broken"
        }
      ]
    },
    {
      "line": "ខ្ញុំសម្ងំធ្វើបទលឺ ក្រាក់ ក្រាក់",
      "translation": "I'm hilarious",
      "phonetic": "khnhom samngom thveu bt lu krak krak",
      "words": [
        {
          "word": "ខ្ញុំ",
          "phonetic": "khnhom",
          "translation": "I"
        },
        {
          "word": "សម្ងំ",
          "phonetic": "samngom",
          "translation": "Hive"
        },
        {
          "word": "ធ្វើ",
          "phonetic": "thveu",
          "translation": "Do"
        },
        {
          "word": "បទ",
          "phonetic": "bt",
          "translation": "Track"
        },
        {
          "word": "លឺ",
          "phonetic": "lu",
          "translation": "Hear"
        },
        {
          "word": "ក្រាក់",
          "phonetic": "krak",
          "translation": "Coin"
        },
        {
          "word": "ក្រាក់",
          "phonetic": "krak",
          "translation": "Coin"
        }
      ]
    },
    {
      "break": true
    },
    {
      "line": "ឥលូវខ្ញុំចេញបទមក ចាក់ ចាក់",
      "translation": "Now I release a song to play",
      "phonetic": "ilouv khnhom chenh bt mk chak chak",
      "words": [
        {
          "word": "ឥលូវ",
          "phonetic": "ilouv",
          "translation": "Now"
        },
        {
          "word": "ខ្ញុំ",
          "phonetic": "khnhom",
          "translation": "I"
        },
        {
          "word": "ចេញ",
          "phonetic": "chenh",
          "translation": "Exit"
        },
        {
          "word": "បទ",
          "phonetic": "bt",
          "translation": "Track"
        },
        {
          "word": "មក",
          "phonetic": "mk",
          "translation": "To come"
        },
        {
          "word": "ចាក់",
          "phonetic": "chak",
          "translation": "Play"
        },
        {
          "word": "ចាក់",
          "phonetic": "chak",
          "translation": "Play"
        }
      ]
    },
    {
      "line": "អោយពួកអាស្អប់ទាំងអស់វាភ្នែកខ្វាក់",
      "translation": "Let all the haters be blind!",
      "phonetic": "aoy puok a saab teangoasa vea phnek khvak",
      "words": [
        {
          "word": "អោយ",
          "phonetic": "aoy",
          "translation": "To"
        },
        {
          "word": "ពួក",
          "phonetic": "puok",
          "translation": "They"
        },
        {
          "word": "អា",
          "phonetic": "a",
          "translation": "Ah"
        },
        {
          "word": "ស្អប់",
          "phonetic": "saab",
          "translation": "Hate"
        },
        {
          "word": "ទាំងអស់",
          "phonetic": "teangoasa",
          "translation": "All"
        },
        {
          "word": "វា",
          "phonetic": "vea",
          "translation": "It"
        },
        {
          "word": "ភ្នែកខ្វាក់",
          "phonetic": "phnek khvak",
          "translation": "Blind"
        }
      ]
    },
    {
      "line": "ម្តេច ម្តេច បានខ្ញុំនេះមុខបាក់",
      "translation": "How can I have this broken face?",
      "phonetic": "mtech  mtech  ban khnhom nih moukh bak",
      "words": [
        {
          "word": "ម្តេច",
          "phonetic": "mte ch",
          "translation": "How"
        },
        {
          "word": "ម្តេច",
          "phonetic": "mte ch",
          "translation": "How"
        },
        {
          "word": "បាន",
          "phonetic": "ban",
          "translation": "Yes"
        },
        {
          "word": "ខ្ញុំ",
          "phonetic": "khnhom",
          "translation": "I"
        },
        {
          "word": "នេះ",
          "phonetic": "nih",
          "translation": "This"
        },
        {
          "word": "មុខ",
          "phonetic": "moukh",
          "translation": "Face"
        },
        {
          "word": "បាក់",
          "phonetic": "bak",
          "translation": "Broken"
        }
      ]
    },
    {
      "line": "ខ្ញុំសម្ងំធ្វើបទលឺ ក្រាក់ ក្រាក់",
      "translation": "I'm hilarious",
      "phonetic": "khnhom samngom thveu bt lu krak krak",
      "words": [
        {
          "word": "ខ្ញុំ",
          "phonetic": "khnhom",
          "translation": "I"
        },
        {
          "word": "សម្ងំ",
          "phonetic": "samngom",
          "translation": "Hive"
        },
        {
          "word": "ធ្វើ",
          "phonetic": "thveu",
          "translation": "Do"
        },
        {
          "word": "បទ",
          "phonetic": "bt",
          "translation": "Track"
        },
        {
          "word": "លឺ",
          "phonetic": "lu",
          "translation": "Hear"
        },
        {
          "word": "ក្រាក់",
          "phonetic": "krak",
          "translation": "Coin"
        },
        {
          "word": "ក្រាក់",
          "phonetic": "krak",
          "translation": "Coin"
        }
      ]
    },
    {
      "break": true
    },
    {
      "line": "ឥលូវខ្ញុំចេញបទមកចាក់ ចាក់",
      "translation": "Now I release a song to play",
      "phonetic": "ilouv khnhom chenh bt mk chak chak",
      "words": [
        {
          "word": "ឥលូវ",
          "phonetic": "ilouv",
          "translation": "Now"
        },
        {
          "word": "ខ្ញុំ",
          "phonetic": "khnhom",
          "translation": "I"
        },
        {
          "word": "ចេញ",
          "phonetic": "chenh",
          "translation": "Exit"
        },
        {
          "word": "បទ",
          "phonetic": "bt",
          "translation": "Track"
        },
        {
          "word": "មក",
          "phonetic": "mk",
          "translation": "To come"
        },
        {
          "word": "ចាក់",
          "phonetic": "chak",
          "translation": "Play"
        },
        {
          "word": "ចាក់",
          "phonetic": "chak",
          "translation": "Play"
        }
      ]
    },
    {
      "line": "អោយពួកអាស្អប់ទាំងអស់វាភ្នែកខ្វាក់",
      "translation": "Let all the haters be blind!",
      "phonetic": "aoy puok a saab teangoasa vea phnek khvak",
      "words": [
        {
          "word": "អោយ",
          "phonetic": "aoy",
          "translation": "To"
        },
        {
          "word": "ពួក",
          "phonetic": "puok",
          "translation": "They"
        },
        {
          "word": "អា",
          "phonetic": "a",
          "translation": "Ah"
        },
        {
          "word": "ស្អប់",
          "phonetic": "saab",
          "translation": "Hate"
        },
        {
          "word": "ទាំងអស់",
          "phonetic": "teangoasa",
          "translation": "All"
        },
        {
          "word": "វា",
          "phonetic": "vea",
          "translation": "It"
        },
        {
          "word": "ភ្នែកខ្វាក់",
          "phonetic": "phnek khvak",
          "translation": "Blind"
        }
      ]
    },
    {
      "line": "ចាក់ ចាក់ ចាក់ ចាក់ក , ចាក់ ចាក់ ចាក់ ចាក់ក",
      "translation": "ចាក់ ចាក់ ចាក់ ចាក់, ចាក់ ចាក់ ចាក់ ចាក់",
      "phonetic": "chak chak chak  chakk , chak chak chak  chakk",
      "words": [
        {
          "word": "ចាក់",
          "phonetic": "chak",
          "translation": "Play"
        },
        {
          "word": "ចាក់",
          "phonetic": "chak",
          "translation": "Play"
        },
        {
          "word": "ចាក់",
          "phonetic": "chak",
          "translation": "Play"
        },
        {
          "word": "ចាក់",
          "phonetic": "chak",
          "translation": "Play"
        },
        {
          "word": "ក",
          "phonetic": "k",
          "translation": "A"
        },
        {
          "word": ",",
          "phonetic": "",
          "translation": ","
        },
        {
          "word": "ចាក់",
          "phonetic": "chak",
          "translation": "Play"
        },
        {
          "word": "ចាក់",
          "phonetic": "chak",
          "translation": "Play"
        },
        {
          "word": "ចាក់",
          "phonetic": "chak",
          "translation": "Play"
        },
        {
          "word": "ចាក់",
          "phonetic": "chak",
          "translation": "Play"
        },
        {
          "word": "ក",
          "phonetic": "k",
          "translation": "A"
        }
      ]
    },
    {
      "line": "ចាក់ ចាក់ ចាក់ ចាក់ក",
      "translation": "Chak Chak Chak Chak",
      "phonetic": "chak chak chak  chakk",
      "words": [
        {
          "word": "ចាក់",
          "phonetic": "chak",
          "translation": "Play"
        },
        {
          "word": "ចាក់",
          "phonetic": "chak",
          "translation": "Play"
        },
        {
          "word": "ចាក់",
          "phonetic": "chak",
          "translation": "Play"
        },
        {
          "word": "ចាក់",
          "phonetic": "chak",
          "translation": "Play"
        },
        {
          "word": "ក",
          "phonetic": "k",
          "translation": "A"
        }
      ]
    },
    {
      "break": true
    },
    {
      "line": "ចាក់ ចាក់ ចាក់ ចាក់ខ្ញុំចេញមកចាក់ ចាក់ ចាក់ ចាក់ក",
      "translation": "Stab stab stab stab me come out stab stab stab",
      "phonetic": "chak chak chak  chak khnhom chenh mk chak chak chak  chakk",
      "words": [
        {
          "word": "ចាក់",
          "phonetic": "chak",
          "translation": "Play"
        },
        {
          "word": "ចាក់",
          "phonetic": "chak",
          "translation": "Play"
        },
        {
          "word": "ចាក់",
          "phonetic": "chak",
          "translation": "Play"
        },
        {
          "word": "ចាក់",
          "phonetic": "chak",
          "translation": "Play"
        },
        {
          "word": "ខ្ញុំ",
          "phonetic": "khnhom",
          "translation": "I"
        },
        {
          "word": "ចេញ",
          "phonetic": "chenh",
          "translation": "Exit"
        },
        {
          "word": "មក",
          "phonetic": "mk",
          "translation": "To come"
        },
        {
          "word": "ចាក់",
          "phonetic": "chak",
          "translation": "Play"
        },
        {
          "word": "ចាក់",
          "phonetic": "chak",
          "translation": "Play"
        },
        {
          "word": "ចាក់",
          "phonetic": "chak",
          "translation": "Play"
        },
        {
          "word": "ចាក់",
          "phonetic": "chak",
          "translation": "Play"
        },
        {
          "word": "ក",
          "phonetic": "k",
          "translation": "A"
        }
      ]
    },
    {
      "line": "ចាក់អាណាពូកែតែស្ករ ចាក់អាណាអាក្រក់អោយវាល្អ",
      "translation": "Ana is good, but sugar is bad, Ana is good",
      "phonetic": "chak ana pouke te skar  chak ana akrak aoy vea la",
      "words": [
        {
          "word": "ចាក់",
          "phonetic": "chak",
          "translation": "Play"
        },
        {
          "word": "អាណា",
          "phonetic": "ana",
          "translation": "Anna"
        },
        {
          "word": "ពូកែ",
          "phonetic": "pouke",
          "translation": "Outstanding"
        },
        {
          "word": "តែ",
          "phonetic": "te",
          "translation": "Tea"
        },
        {
          "word": "ស្ករ",
          "phonetic": "skar",
          "translation": "Sugar"
        },
        {
          "word": "ចាក់",
          "phonetic": "chak",
          "translation": "Play"
        },
        {
          "word": "អាណា",
          "phonetic": "ana",
          "translation": "Anna"
        },
        {
          "word": "អាក្រក់",
          "phonetic": "akrak",
          "translation": "Bad"
        },
        {
          "word": "អោយ",
          "phonetic": "aoy",
          "translation": "To"
        },
        {
          "word": "វា",
          "phonetic": "vea",
          "translation": "It"
        },
        {
          "word": "ល្អ",
          "phonetic": "la",
          "translation": "Good"
        }
      ]
    },
    {
      "line": "ចាក់អាណាខ្មៅអោយវាស ចាក់កយកកំណប់",
      "translation": "Stab Ana Khmao with a knife",
      "phonetic": "chak ana khmaw aoy veasa  chak k yk kamnb",
      "words": [
        {
          "word": "ចាក់",
          "phonetic": "chak",
          "translation": "Play"
        },
        {
          "word": "អាណា",
          "phonetic": "ana",
          "translation": "Anna"
        },
        {
          "word": "ខ្មៅ",
          "phonetic": "khmaw",
          "translation": "Black"
        },
        {
          "word": "អោយ",
          "phonetic": "aoy",
          "translation": "To"
        },
        {
          "word": "វាស",
          "phonetic": "veasa",
          "translation": "Veas"
        },
        {
          "word": "ចាក់",
          "phonetic": "chak",
          "translation": "Play"
        },
        {
          "word": "ក",
          "phonetic": "k",
          "translation": "A"
        },
        {
          "word": "យក",
          "phonetic": "yk",
          "translation": "Take"
        },
        {
          "word": "កំណប់",
          "phonetic": "kamnb",
          "translation": "Treasure"
        }
      ]
    },
    {
      "line": "រកលុយជូនគ្រួសារ ប៉ុន្មានឆ្នាំនេះចង់សន្លប់",
      "translation": "Make money for the family, these years want to faint",
      "phonetic": "roklouy choun kruosaear  bonman chhnam nih chng sanlob",
      "words": [
        {
          "word": "រកលុយ",
          "phonetic": "roklouy",
          "translation": "Make money"
        },
        {
          "word": "ជូន",
          "phonetic": "choun",
          "translation": "To"
        },
        {
          "word": "គ្រួសារ",
          "phonetic": "kruosaear",
          "translation": "Family"
        },
        {
          "word": "ប៉ុន្មាន",
          "phonetic": "bonman",
          "translation": "How much"
        },
        {
          "word": "ឆ្នាំ",
          "phonetic": "chhnam",
          "translation": "Years"
        },
        {
          "word": "នេះ",
          "phonetic": "nih",
          "translation": "This"
        },
        {
          "word": "ចង់",
          "phonetic": "chng",
          "translation": "Want"
        },
        {
          "word": "សន្លប់",
          "phonetic": "sanlob",
          "translation": "Unconscious"
        }
      ]
    },
    {
      "break": true
    },
    {
      "line": "ដណ្តប់ភួយដូចដណ្តប់ផ្កា តែពេលនេះថ្ងៃនេះខ្ញុំអ្នកកប់",
      "translation": "Covered with a blanket like a flower, but now I am burying",
      "phonetic": "dantabphuoy dauch d nt b phka  te pelnih thngainih khnhom anak kb",
      "words": [
        {
          "word": "ដណ្តប់",
          "phonetic": "d nt b",
          "translation": "Cover"
        },
        {
          "word": "ភួយ",
          "phonetic": "phuoy",
          "translation": "Blanket"
        },
        {
          "word": "ដូច",
          "phonetic": "dauch",
          "translation": "Like"
        },
        {
          "word": "ដណ្តប់",
          "phonetic": "d nt b",
          "translation": "Cover"
        },
        {
          "word": "ផ្កា",
          "phonetic": "phka",
          "translation": "Flowers"
        },
        {
          "word": "តែ",
          "phonetic": "te",
          "translation": "Tea"
        },
        {
          "word": "ពេលនេះ",
          "phonetic": "pelnih",
          "translation": "Now"
        },
        {
          "word": "ថ្ងៃនេះ",
          "phonetic": "thngainih",
          "translation": "Today"
        },
        {
          "word": "ខ្ញុំ",
          "phonetic": "khnhom",
          "translation": "I"
        },
        {
          "word": "អ្នក",
          "phonetic": "anak",
          "translation": "You"
        },
        {
          "word": "កប់",
          "phonetic": "kb",
          "translation": "Bury"
        }
      ]
    },
    {
      "line": "សពពួកអាចិត្តឬស្យា ពួកអានេះវាពូកែសន្លប់",
      "translation": "ស ប ពួក អា ចិត្ត⁇ ស្យា ពួក អា នេះ",
      "phonetic": "sa ppuok a chett ryy sya  puok a nih vea pouke sanlob",
      "words": [
        {
          "word": "សព",
          "phonetic": "sap",
          "translation": "Corpse"
        },
        {
          "word": "ពួក",
          "phonetic": "puok",
          "translation": "They"
        },
        {
          "word": "អា",
          "phonetic": "a",
          "translation": "Ah"
        },
        {
          "word": "ចិត្ត",
          "phonetic": "chett",
          "translation": "Mind"
        },
        {
          "word": "ឬ",
          "phonetic": "ryy",
          "translation": "Or"
        },
        {
          "word": "ស្យា",
          "phonetic": "sya",
          "translation": "ស្យា"
        },
        {
          "word": "ពួក",
          "phonetic": "puok",
          "translation": "They"
        },
        {
          "word": "អានេះ",
          "phonetic": "anih",
          "translation": "Ah this"
        },
        {
          "word": "វា",
          "phonetic": "vea",
          "translation": "It"
        },
        {
          "word": "ពូកែ",
          "phonetic": "pouke",
          "translation": "Outstanding"
        },
        {
          "word": "សន្លប់",
          "phonetic": "sanlob",
          "translation": "Unconscious"
        }
      ]
    },
    {
      "line": "នៅមុខវាដូចអ្នកតា វាមុខមួយ វាមុខពីរ វាមុខបី ពួកអាក្របី",
      "translation": "In front of it, like you, it has one face, it has two faces, it has three faces,",
      "phonetic": "nowmoukh vea dauch anaktea  vea moukh muoy  vea moukh pir  vea moukh bei  puok akrabei",
      "words": [
        {
          "word": "នៅមុខ",
          "phonetic": "nowmoukh",
          "translation": "In front"
        },
        {
          "word": "វា",
          "phonetic": "vea",
          "translation": "It"
        },
        {
          "word": "ដូច",
          "phonetic": "dauch",
          "translation": "Like"
        },
        {
          "word": "អ្នកតា",
          "phonetic": "anaktea",
          "translation": "Nephew"
        },
        {
          "word": "វា",
          "phonetic": "vea",
          "translation": "It"
        },
        {
          "word": "មុខ",
          "phonetic": "moukh",
          "translation": "Face"
        },
        {
          "word": "មួយ",
          "phonetic": "muoy",
          "translation": "One"
        },
        {
          "word": "វា",
          "phonetic": "vea",
          "translation": "It"
        },
        {
          "word": "មុខ",
          "phonetic": "moukh",
          "translation": "Face"
        },
        {
          "word": "ពីរ",
          "phonetic": "pir",
          "translation": "Two"
        },
        {
          "word": "វា",
          "phonetic": "vea",
          "translation": "It"
        },
        {
          "word": "មុខ",
          "phonetic": "moukh",
          "translation": "Face"
        },
        {
          "word": "បី",
          "phonetic": "bei",
          "translation": "Three"
        },
        {
          "word": "ពួក",
          "phonetic": "puok",
          "translation": "They"
        },
        {
          "word": "អា",
          "phonetic": "a",
          "translation": "Ah"
        },
        {
          "word": "ក្របី",
          "phonetic": "krabei",
          "translation": "Buffalo"
        }
      ]
    },
    {
      "line": "ខ្ញុំចាប់វាលាងខួរ ចាប់ពួកអាតូ ចាប់វាញីដី",
      "translation": "I caught it, washed my brain, caught the Ato, caught it on the ground",
      "phonetic": "khnhom chab vea leang khuor  chab puok a tau  chab vea nhi dei",
      "words": [
        {
          "word": "ខ្ញុំ",
          "phonetic": "khnhom",
          "translation": "I"
        },
        {
          "word": "ចាប់",
          "phonetic": "chab",
          "translation": "Catch"
        },
        {
          "word": "វា",
          "phonetic": "vea",
          "translation": "It"
        },
        {
          "word": "លាង",
          "phonetic": "leang",
          "translation": "Wash"
        },
        {
          "word": "ខួរ",
          "phonetic": "khuor",
          "translation": "Brain"
        },
        {
          "word": "ចាប់",
          "phonetic": "chab",
          "translation": "Catch"
        },
        {
          "word": "ពួក",
          "phonetic": "puok",
          "translation": "They"
        },
        {
          "word": "អា",
          "phonetic": "a",
          "translation": "Ah"
        },
        {
          "word": "តូ",
          "phonetic": "tau",
          "translation": "To"
        },
        {
          "word": "ចាប់",
          "phonetic": "chab",
          "translation": "Catch"
        },
        {
          "word": "វា",
          "phonetic": "vea",
          "translation": "It"
        },
        {
          "word": "ញី",
          "phonetic": "nhi",
          "translation": "Female"
        },
        {
          "word": "ដី",
          "phonetic": "dei",
          "translation": "Land"
        }
      ]
    },
    {
      "line": "UNBELIEVABLE គេសួរខ្ញុំ TOP 3 តើខ្ញុំបានអី",
      "translation": "UNBELIEVABLE They ask me TOP 3, what did I get?",
      "phonetic": "unbelievable  ke suor khnhom top 3  tae khnhom ban ei",
      "words": [
        {
          "word": "UNBELIEVABLE",
          "phonetic": "",
          "translation": "UNBELIEVABLE"
        },
        {
          "word": "គេ",
          "phonetic": "ke",
          "translation": "They"
        },
        {
          "word": "សួរ",
          "phonetic": "suor",
          "translation": "Ask"
        },
        {
          "word": "ខ្ញុំ",
          "phonetic": "khnhom",
          "translation": "I"
        },
        {
          "word": "TOP",
          "phonetic": "",
          "translation": "TOP"
        },
        {
          "word": "3",
          "phonetic": "",
          "translation": "3"
        },
        {
          "word": "តើ",
          "phonetic": "tae",
          "translation": "Is"
        },
        {
          "word": "ខ្ញុំ",
          "phonetic": "khnhom",
          "translation": "I"
        },
        {
          "word": "បាន",
          "phonetic": "ban",
          "translation": "Yes"
        },
        {
          "word": "អី",
          "phonetic": "ei",
          "translation": "What"
        }
      ]
    },
    {
      "break": true
    },
    {
      "line": "ខ្ញុំថាបានស្ពៃបើបទមិន GO VIRAL ប្រហែលជាខ្ញុំដាច់ពោះ",
      "translation": "I said yes, if the song is not GO VIRAL, maybe I'm hungry",
      "phonetic": "khnhom tha ban spai bae bt min go viral  brahelcha khnhom dachpoh",
      "words": [
        {
          "word": "ខ្ញុំ",
          "phonetic": "khnhom",
          "translation": "I"
        },
        {
          "word": "ថា",
          "phonetic": "tha",
          "translation": "That"
        },
        {
          "word": "បាន",
          "phonetic": "ban",
          "translation": "Yes"
        },
        {
          "word": "ស្ពៃ",
          "phonetic": "spai",
          "translation": "Cabbage"
        },
        {
          "word": "បើ",
          "phonetic": "bae",
          "translation": "If"
        },
        {
          "word": "បទ",
          "phonetic": "bt",
          "translation": "Track"
        },
        {
          "word": "មិន",
          "phonetic": "min",
          "translation": "No"
        },
        {
          "word": "GO",
          "phonetic": "",
          "translation": "GO"
        },
        {
          "word": "VIRAL",
          "phonetic": "",
          "translation": "VIRAL"
        },
        {
          "word": "ប្រហែលជា",
          "phonetic": "brahelcha",
          "translation": "Maybe"
        },
        {
          "word": "ខ្ញុំ",
          "phonetic": "khnhom",
          "translation": "I"
        },
        {
          "word": "ដាច់",
          "phonetic": "dach",
          "translation": "Isolated"
        },
        {
          "word": "ពោះ",
          "phonetic": "poh",
          "translation": "Belly"
        }
      ]
    },
    {
      "line": "ខ្ញុំចង់បោះក្រដាសប្រាក់ ប្រាក់ ប្រាក់ ប្រាក់ ឡើងទៅលើមេឃ",
      "translation": "I want to throw money, money, money into the sky",
      "phonetic": "khnhom chng baoh kradeasabrak brak brak brak  laeng towleu mekh",
      "words": [
        {
          "word": "ខ្ញុំ",
          "phonetic": "khnhom",
          "translation": "I"
        },
        {
          "word": "ចង់",
          "phonetic": "chng",
          "translation": "Want"
        },
        {
          "word": "បោះ",
          "phonetic": "baoh",
          "translation": "Throw"
        },
        {
          "word": "ក្រដាសប្រាក់",
          "phonetic": "kradeasabrak",
          "translation": "Banknote"
        },
        {
          "word": "ប្រាក់",
          "phonetic": "brak",
          "translation": "Money"
        },
        {
          "word": "ប្រាក់",
          "phonetic": "brak",
          "translation": "Money"
        },
        {
          "word": "ប្រាក់",
          "phonetic": "brak",
          "translation": "Money"
        },
        {
          "word": "ឡើង",
          "phonetic": "laeng",
          "translation": "Up"
        },
        {
          "word": "ទៅ",
          "phonetic": "tow",
          "translation": "To"
        },
        {
          "word": "លើមេឃ",
          "phonetic": "leumekh",
          "translation": "In the sky"
        }
      ]
    },
    {
      "line": "ប្រាក់ ប្រាក់ ប្រាក់ ប្រាក់ឡើងទៅលើមេឃ",
      "translation": "Money, money, money goes up to the sky",
      "phonetic": "brak brak brak  brak laeng tow leumekh",
      "words": [
        {
          "word": "ប្រាក់",
          "phonetic": "brak",
          "translation": "Money"
        },
        {
          "word": "ប្រាក់",
          "phonetic": "brak",
          "translation": "Money"
        },
        {
          "word": "ប្រាក់",
          "phonetic": "brak",
          "translation": "Money"
        },
        {
          "word": "ប្រាក់",
          "phonetic": "brak",
          "translation": "Money"
        },
        {
          "word": "ឡើង",
          "phonetic": "laeng",
          "translation": "Up"
        },
        {
          "word": "ទៅ",
          "phonetic": "tow",
          "translation": "To"
        },
        {
          "word": "លើមេឃ",
          "phonetic": "leumekh",
          "translation": "In the sky"
        }
      ]
    },
    {
      "break": true
    },
    {
      "line": "បោះក្រដាសប្រាក់ ប្រាក់ ប្រាក់ ប្រាក់ ឡើងទៅលើមេឃ",
      "translation": "Throw money banknotes into the sky",
      "phonetic": "baoh kradeasabrak brak brak brak  laeng towleu mekh",
      "words": [
        {
          "word": "បោះ",
          "phonetic": "baoh",
          "translation": "Throw"
        },
        {
          "word": "ក្រដាសប្រាក់",
          "phonetic": "kradeasabrak",
          "translation": "Banknote"
        },
        {
          "word": "ប្រាក់",
          "phonetic": "brak",
          "translation": "Money"
        },
        {
          "word": "ប្រាក់",
          "phonetic": "brak",
          "translation": "Money"
        },
        {
          "word": "ប្រាក់",
          "phonetic": "brak",
          "translation": "Money"
        },
        {
          "word": "ឡើង",
          "phonetic": "laeng",
          "translation": "Up"
        },
        {
          "word": "ទៅ",
          "phonetic": "tow",
          "translation": "To"
        },
        {
          "word": "លើមេឃ",
          "phonetic": "leumekh",
          "translation": "In the sky"
        }
      ]
    },
    {
      "line": "ប្រាក់ ប្រាក់ ប្រាក់ ប្រាក់ឡើងទៅលើមេឃ",
      "translation": "Money, money, money goes up to the sky",
      "phonetic": "brak brak brak  brak laeng tow leumekh",
      "words": [
        {
          "word": "ប្រាក់",
          "phonetic": "brak",
          "translation": "Money"
        },
        {
          "word": "ប្រាក់",
          "phonetic": "brak",
          "translation": "Money"
        },
        {
          "word": "ប្រាក់",
          "phonetic": "brak",
          "translation": "Money"
        },
        {
          "word": "ប្រាក់",
          "phonetic": "brak",
          "translation": "Money"
        },
        {
          "word": "ឡើង",
          "phonetic": "laeng",
          "translation": "Up"
        },
        {
          "word": "ទៅ",
          "phonetic": "tow",
          "translation": "To"
        },
        {
          "word": "លើមេឃ",
          "phonetic": "leumekh",
          "translation": "In the sky"
        }
      ]
    }
  ]
}