{
  "id": "essentials",
  "label": "Essentials & Verbs",
  "chunkSizes": [
    10,
    10,
    10,
    9
  ],
  "words": [
    {
      "word": "សួស្តី",
      "translation": "Hello",
      "phonetic": "Suostei"
    },
    {
      "word": "បាទ",
      "translation": "Yes [Male]",
      "phonetic": "Baat"
    },
    {
      "word": "ចាស",
      "translation": "Yes [Female]",
      "phonetic": "Jaas"
    },
    {
      "word": "ទេ",
      "translation": "No",
      "phonetic": "Te"
    },
    {
      "word": "អរគុណ",
      "translation": "Thank you",
      "phonetic": "Orkun"
    },
    {
      "word": "សូម",
      "translation": "Please",
      "phonetic": "Som"
    },
    {
      "word": "សូមទោស",
      "translation": "Sorry / Excuse me",
      "phonetic": "Som tos"
    },
    {
      "word": "លាហើយ",
      "translation": "Goodbye",
      "phonetic": "Lea huey"
    },
    {
      "word": "ខ្ញុំ",
      "translation": "I / Me",
      "phonetic": "Knhom"
    },
    {
      "word": "អ្នក",
      "translation": "You",
      "phonetic": "Neak"
    },
    {
      "word": "គាត់",
      "translation": "He / She",
      "phonetic": "Koat"
    },
    {
      "word": "ពួកយើង",
      "translation": "We",
      "phonetic": "Puok yeung"
    },
    {
      "word": "គេ",
      "translation": "They",
      "phonetic": "Ke"
    },
    {
      "word": "នេះ",
      "translation": "This",
      "phonetic": "Nih"
    },
    {
      "word": "នោះ",
      "translation": "That",
      "phonetic": "Nuh"
    },
    {
      "word": "ទៅ",
      "translation": "Go",
      "phonetic": "Tov"
    },
    {
      "word": "មក",
      "translation": "Come",
      "phonetic": "Mok"
    },
    {
      "word": "ញ៉ាំ",
      "translation": "Eat",
      "phonetic": "Nham"
    },
    {
      "word": "ផឹក",
      "translation": "Drink",
      "phonetic": "Phok"
    },
    {
      "word": "ចង់",
      "translation": "Want",
      "phonetic": "Chong"
    },
    {
      "word": "មាន",
      "translation": "Have",
      "phonetic": "Mean"
    },
    {
      "word": "ធ្វើ",
      "translation": "Do / Make",
      "phonetic": "Thveu"
    },
    {
      "word": "ដឹង",
      "translation": "Know",
      "phonetic": "Deung"
    },
    {
      "word": "យល់",
      "translation": "Understand",
      "phonetic": "Yol"
    },
    {
      "word": "អាច",
      "translation": "Can",
      "phonetic": "Ach"
    },
    {
      "word": "ចូលចិត្ត",
      "translation": "Like",
      "phonetic": "Choul chet"
    },
    {
      "word": "សុខសប្បាយទេ",
      "translation": "How are you?",
      "phonetic": "Sok sabay te?"
    },
    {
      "word": "ល្អ",
      "translation": "Good",
      "phonetic": "La'or"
    },
    {
      "word": "អាក្រក់",
      "translation": "Bad",
      "phonetic": "Akrok"
    },
    {
      "word": "ធំ",
      "translation": "Big",
      "phonetic": "Thom"
    },
    {
      "word": "តូច",
      "translation": "Small",
      "phonetic": "Touch"
    },
    {
      "word": "ច្រើន",
      "translation": "A lot / Much",
      "phonetic": "Chraen"
    },
    {
      "word": "តិច",
      "translation": "A little",
      "phonetic": "Tech"
    },
    {
      "word": "អ្វី",
      "translation": "What",
      "phonetic": "Avey"
    },
    {
      "word": "នៅឯណា",
      "translation": "Where",
      "phonetic": "Nov aena"
    },
    {
      "word": "ពេលណា",
      "translation": "When",
      "phonetic": "Pel na"
    },
    {
      "word": "ហេតុអ្វី",
      "translation": "Why",
      "phonetic": "Het avey"
    },
    {
      "word": "អ្នកណា",
      "translation": "Who",
      "phonetic": "Neak na"
    },
    {
      "word": "ប៉ុន្មាន",
      "translation": "How much / How many",
      "phonetic": "Ponman"
    }
  ]
}